backbone/__init__.py
backbone/apps.py
backbone/entities.py
backbone/entity_streams.py
backbone/extensions.py
backbone/vendored/task_groups.py
app_backbone-0.0.2.dist-info/LICENSE
app_backbone-0.0.2.dist-info/METADATA
app_backbone-0.0.2.dist-info/WHEEL
app_backbone-0.0.2.dist-info/RECORD
